LICENSE.txt
MANIFEST.in
README.md
README.rst
setup.py
bin/multiping.py
jk_trioping/__init__.py
jk_trioping/trioping.py
jk_trioping.egg-info/PKG-INFO
jk_trioping.egg-info/SOURCES.txt
jk_trioping.egg-info/dependency_links.txt
jk_trioping.egg-info/not-zip-safe
jk_trioping.egg-info/requires.txt
jk_trioping.egg-info/top_level.txt