Metadata-Version: 2.1
Name: jk-trioping
Version: 0.2020.4.1
Summary: This python module provides an asynchroneous version of ping. It is based on the trio framework.
Home-page: https://github.com/jkpubsrc/python-module-jk-trioping
Author: Jürgen Knauth
Author-email: pubsrc@binary-overflow.de
License: Apache 2.0
Download-URL: https://github.com/jkpubsrc/python-module-jk-trioping/tarball/0.2020.4.1
Keywords: trio,ping
Platform: UNKNOWN
Classifier: Development Status :: 3 - Alpha
Classifier: Framework :: Trio
Classifier: License :: OSI Approved :: Apache Software License
